.DS_Store
cbgt.cpython-36m-darwin.so
CBGT-0.0.6.dist-info/DESCRIPTION.rst
CBGT-0.0.6.dist-info/METADATA
CBGT-0.0.6.dist-info/RECORD
CBGT-0.0.6.dist-info/WHEEL
CBGT-0.0.6.dist-info/metadata.json
CBGT-0.0.6.dist-info/top_level.txt
cbgt/__init__.py
cbgt/analyzefx.py
cbgt/netgen.py
cbgt/sim.py
cbgt/vis.py
cbgt/docs/0.txt
cbgt/docs/1.txt
cbgt/docs/10.txt
cbgt/docs/11.txt
cbgt/docs/12.txt
cbgt/docs/13.txt
cbgt/docs/14.txt
cbgt/docs/15.txt
cbgt/docs/2.txt
cbgt/docs/3.txt
cbgt/docs/4.txt
cbgt/docs/5.txt
cbgt/docs/6.txt
cbgt/docs/7.txt
cbgt/docs/8.txt
cbgt/docs/9.txt
cbgt/docs/SimulatorDocs.md
cbgt/docs/netgendoc.txt
cbgt/params/Ctx.py
cbgt/params/FSI.py
cbgt/params/GPe.py
cbgt/params/GPi.py
cbgt/params/LIPI.py
cbgt/params/STN.py
cbgt/params/Thal.py
cbgt/params/cbgt_conn_table.tex
cbgt/params/dMSN_Left.py
cbgt/params/dMSN_Right.py
cbgt/params/iMSN_Left.py
cbgt/params/iMSN_Right.py
cbgt/src/cbgt.c
cbgt/src/rando2.h
