Metadata-Version: 2.0
Name: CBGT
Version: 0.0.6
Summary: CBGT contains code for implementing the CBGT network and drift-diffusion model (DDM) fits described in the manuscript Reward-driven changes in striatal pathway competition shape evidence evaluation in decision-making.
Home-page: http://github.com/CoAxLab/CBGT
Author: Kyle Dunovan, Catalina Vich, Matthew Clapp, Timothy Verstynen, Jonathan Rubin, Wei Wei, and Xiao Jing Wang
Author-email: dunovank@gmail.com
License: UNKNOWN
Platform: UNKNOWN
Classifier: Environment :: Console
Classifier: Operating System :: OS Independent
Classifier: License :: OSI Approved :: BSD License
Classifier: Intended Audience :: Science/Research
Classifier: Development Status :: 3 - Alpha
Classifier: Programming Language :: Python
Classifier: Programming Language :: Python :: 3
Classifier: Programming Language :: Python :: 3.6
Classifier: Topic :: Scientific/Engineering
Requires-Dist: numpy (==1.11.3)
Requires-Dist: pandas (>=0.15.1)
Requires-Dist: matplotlib (>=1.4.3)
Requires-Dist: seaborn (>=0.5.1)
Requires-Dist: future
